vtiles/__init__.py
vtiles/mbtiles/__init__.py
vtiles/mbtiles/flipy.py
vtiles/mbtiles/folder2mbtiles.py
vtiles/mbtiles/folder2s3.py
vtiles/mbtiles/geojson2mbtiles.py
vtiles/mbtiles/mbtiles2folder.py
vtiles/mbtiles/mbtiles2geojson.py
vtiles/mbtiles/mbtiles2pbf.py
vtiles/mbtiles/mbtiles2pmtiles.py
vtiles/mbtiles/mbtiles2s3.py
vtiles/mbtiles/mbtilescompress.py
vtiles/mbtiles/mbtilesdecompress.py
vtiles/mbtiles/mbtilesdelduplicate.py
vtiles/mbtiles/mbtilesfixmeta.py
vtiles/mbtiles/mbtilesfixmeta_old.py
vtiles/mbtiles/mbtilesinfo.py
vtiles/mbtiles/mbtilesinspect.py
vtiles/mbtiles/mbtilesmerge.py
vtiles/mbtiles/mbtilessplit.py
vtiles/mbtiles/pbf2geojson.py
vtiles/mbtiles/pbfinfo.py
vtiles/mbtiles/url2folder.py
vtiles/server/__init__.py
vtiles/server/servefolder.py
vtiles/server/servembtiles.py
vtiles/server/servepmtiles.py
vtiles/server/servepostgis.py
vtiles/server/serverastermbtiles.py
vtiles/server/servevectormbtiles.py
vtiles/utils/__init__.py
vtiles/utils/centerline.py
vtiles/utils/geopreocessing.py
vtiles/utils/mbtiles2s3.py
vtiles/utils/pmtiles2folder.py
vtiles/utils/pmtiles2mbtiles.py
vtiles/utils/pmtilesinfo.py
vtiles/utils/vtpk2folder.py
vtiles/utils/geojson2vt/__init__.py
vtiles/utils/geojson2vt/clip.py
vtiles/utils/geojson2vt/convert.py
vtiles/utils/geojson2vt/feature.py
vtiles/utils/geojson2vt/geojson2vt.py
vtiles/utils/geojson2vt/simplify.py
vtiles/utils/geojson2vt/tile.py
vtiles/utils/geojson2vt/transform.py
vtiles/utils/geojson2vt/utils.py
vtiles/utils/geojson2vt/vt2geojson.py
vtiles/utils/geojson2vt/wrap.py
vtiles/utils/label_centerlines/__init__.py
vtiles/utils/label_centerlines/_src.py
vtiles/utils/label_centerlines/cli.py
vtiles/utils/label_centerlines/exceptions.py
vtiles/utils/mapbox_vector_tile/__init__.py
vtiles/utils/mapbox_vector_tile/decoder.py
vtiles/utils/mapbox_vector_tile/encoder.py
vtiles/utils/mapbox_vector_tile/geom_encoder.py
vtiles/utils/mapbox_vector_tile/optimise.py
vtiles/utils/mapbox_vector_tile/polygon.py
vtiles-1.0.7.dist-info/LICENSE
vtiles-1.0.7.dist-info/METADATA
vtiles-1.0.7.dist-info/WHEEL
vtiles-1.0.7.dist-info/entry_points.txt
vtiles-1.0.7.dist-info/top_level.txt
vtiles-1.0.7.dist-info/RECORD
